bookchain/__init__.py
bookchain/version.py
bookchain/asyncql/Account.py
bookchain/asyncql/AccountCategory.py
bookchain/asyncql/AccountType.py
bookchain/asyncql/ArchivedEntry.py
bookchain/asyncql/ArchivedTransaction.py
bookchain/asyncql/Correspondence.py
bookchain/asyncql/Currency.py
bookchain/asyncql/Customer.py
bookchain/asyncql/Entry.py
bookchain/asyncql/EntryType.py
bookchain/asyncql/Identity.py
bookchain/asyncql/Ledger.py
bookchain/asyncql/LedgerType.py
bookchain/asyncql/Transaction.py
bookchain/asyncql/TxRollup.py
bookchain/asyncql/Vendor.py
bookchain/asyncql/__init__.py
bookchain/models/Account.py
bookchain/models/AccountCategory.py
bookchain/models/AccountType.py
bookchain/models/ArchivedEntry.py
bookchain/models/ArchivedTransaction.py
bookchain/models/Correspondence.py
bookchain/models/Currency.py
bookchain/models/Customer.py
bookchain/models/Entry.py
bookchain/models/EntryType.py
bookchain/models/Identity.py
bookchain/models/Ledger.py
bookchain/models/LedgerType.py
bookchain/models/Transaction.py
bookchain/models/TxRollup.py
bookchain/models/Vendor.py
bookchain/models/__init__.py
bookchain-0.3.2.dist-info/METADATA
bookchain-0.3.2.dist-info/WHEEL
bookchain-0.3.2.dist-info/RECORD
