Metadata-Version: 2.4
Name: bookchain
Version: 0.3.2
Summary: Double-entry accounting system with cryptographic audit trail and optional cryptographic transaction verification.
Project-URL: Homepage, https://github.com/k98kurz/bookchain
Project-URL: Repository, https://github.com/k98kurz/bookchain
Project-URL: Bug Tracker, https://github.com/k98kurz/bookchain/issues
Author-email: k98kurz <k98kurz@gmail.com>
License: Copyright (c) 2025 Jonathan Voss (k98kurz)
Classifier: Development Status :: 3 - Alpha
Classifier: License :: Free for non-commercial use
Classifier: Operating System :: OS Independent
Classifier: Programming Language :: Python :: 3
Classifier: Topic :: Database :: Front-Ends
Classifier: Topic :: Office/Business :: Financial :: Accounting
Requires-Python: >=3.10
Requires-Dist: merkleasy>=0.1.2
Requires-Dist: packify>=0.3.1
Requires-Dist: sqloquent>=0.7.0
Requires-Dist: tapescript>=0.7.2
Provides-Extra: asyncql
Requires-Dist: sqloquent[asyncql]>=0.7.0; extra == 'asyncql'
Provides-Extra: docs
Requires-Dist: autodox>=0.1.16; extra == 'docs'
